socketify/__init__.py
socketify/__main__.py
socketify/asgi.py
socketify/cli.py
socketify/dataclasses.py
socketify/helpers.py
socketify/libsocketify_darwin_amd64.so
socketify/libsocketify_darwin_arm64.so
socketify/libsocketify_linux_amd64.so
socketify/libsocketify_windows_amd64.dll
socketify/loop.py
socketify/native.py
socketify/socketify.py
socketify/ssgi.py
socketify/status_codes.py
socketify/tasks.py
socketify/uv.py
socketify/wsgi.py
socketify/native/Make.bat
socketify/native/Makefile
socketify/native/uv_selector.txt
socketify/native/src/libsocketify.cpp
socketify/native/src/libsocketify.h
socketify-0.0.31.dist-info/LICENSE
socketify-0.0.31.dist-info/METADATA
socketify-0.0.31.dist-info/WHEEL
socketify-0.0.31.dist-info/top_level.txt
socketify-0.0.31.dist-info/RECORD
