Metadata-Version: 2.1
Name: socketify
Version: 0.0.31
Summary: Bringing WebSockets, Http/Https High Performance servers for PyPy3 and Python3
Home-page: https://github.com/cirospaciari/socketify.py
Author: Ciro Spaciari
Author-email: Ciro Spaciari <ciro.spaciari@gmail.com>
Project-URL: Homepage, https://github.com/cirospaciari/socketify.py
Project-URL: Bug Tracker, https://github.com/cirospaciari/socketify.py/issues
Platform: any
Classifier: Programming Language :: Python :: 3
Classifier: License :: OSI Approved :: MIT License
Classifier: Operating System :: OS Independent
Requires-Python: >=3.8
License-File: LICENSE
Requires-Dist: cffi >=1.0
Requires-Dist: setuptools >=58.1.0
